gamest_plugins/retroarch_identifier/__init__.py
gamest_plugins/retroarch_identifier/module.py
gamest_retroarch_identifier_plugin-1.0.1.dist-info/METADATA
gamest_retroarch_identifier_plugin-1.0.1.dist-info/WHEEL
gamest_retroarch_identifier_plugin-1.0.1.dist-info/top_level.txt
gamest_retroarch_identifier_plugin-1.0.1.dist-info/RECORD
