Metadata-Version: 2.1
Name: gamest-retroarch-identifier-plugin
Version: 1.0.1
Summary: Identify games running in retroarch.
Home-page: https://github.com/sopoforic/gamest_retroarch_identifier_plugin
Author: Tracy Poff
Author-email: tracy.poff@gmail.com
Classifier: Development Status :: 4 - Beta
Classifier: Environment :: Win32 (MS Windows)
Classifier: Intended Audience :: End Users/Desktop
Classifier: License :: OSI Approved :: GNU General Public License v3 or later (GPLv3+)
Classifier: Programming Language :: Python :: 3
Classifier: Topic :: Games/Entertainment
Requires-Dist: gamest <5.0,>=4.1
Requires-Dist: pyraco
